classification_model/VERSION
classification_model/__init__.py
classification_model/config.yml
classification_model/pipeline.py
classification_model/predict.py
classification_model/train_pipeline.py
classification_model/config/__init__.py
classification_model/config/core.py
classification_model/datasets/__init__.py
classification_model/datasets/test_titanic.csv
classification_model/datasets/train_titanic.csv
classification_model/processing/__init__.py
classification_model/processing/data_manager.py
classification_model/processing/features.py
classification_model/processing/validation.py
classification_model/trained_models/__init__.py
classification_model/trained_models/classification_model_output_v0.0.1.pkl
classification_model_titanic_david_anthony-0.0.1.dist-info/LICENSE
classification_model_titanic_david_anthony-0.0.1.dist-info/METADATA
classification_model_titanic_david_anthony-0.0.1.dist-info/WHEEL
classification_model_titanic_david_anthony-0.0.1.dist-info/top_level.txt
classification_model_titanic_david_anthony-0.0.1.dist-info/RECORD
